{
  "data": [
    {
      "id": 33860,
      "attributes": {
        "diary_hour": "16:45:00",
        "diary_description": "Copa Argentina: Racing Club vs Defensa y Justicia",
        "date_diary": "2026-07-16",
        "deportes": "Futbol",
        "embeds": {
          "data": [
            {
              "id": 101,
              "attributes": {
                "embed_name": "TyC Sports",
                "idioma": "español",
                "embed_iframe": "/embed/eventos.html?r=aHR0cHM6Ly9sYTIwaGQuY29tL3Zpdm8vY2FuYWwucGhwP3N0cmVhbT10eWNzcG9ydHM="
              }
            },
            {
              "id": 1211,
              "attributes": {
                "embed_name": "TyC Sports Movil",
                "idioma": null,
                "embed_iframe": "/embed/eventos?r=aHR0cHM6Ly93d3cudGFyamV0YXJvaml0YS54eXovc3czLmh0bWw/Z2V0PWh0dHBzOi8vd3d3LnRhcmpldGFyb2ppdGEueHl6L3JlcHJvL3R5Y3Nwb3J0c2FyZy5odG1s"
              }
            },
            {
              "id": 20747,
              "attributes": {
                "embed_name": "TyC Sports",
                "idioma": "Español/Alternativo",
                "embed_iframe": "/eventos.html?r=aHR0cHM6Ly9zdHJlYW10cC5zYnMvZ2xvYmFsMS5waHA/c3RyZWFtPXR5Y3Nwb3J0cw=="
              }
            },
            {
              "id": 18569,
              "attributes": {
                "embed_name": "Fanatiz",
                "idioma": "Español/Alternativo",
                "embed_iframe": "/eventos.html?r=aHR0cHM6Ly9zdHJlYW14OTk2Lm9uZS9nbG9iYWwxLnBocD9jaGFubmVsPWZhbmF0aXox"
              }
            },
            {
              "id": 26477,
              "attributes": {
                "embed_name": "TyC Sports OP2",
                "idioma": "Español/Alternativo",
                "embed_iframe": "/eventos.html?r=aHR0cHM6Ly9zdHJlYW14OTk2Lm9uZS9nbG9iYWwxLnBocD9jaGFubmVsPXR5Yw=="
              }
            },
            {
              "id": 11438,
              "attributes": {
                "embed_name": "TyC Sports Internacional",
                "idioma": "Español/Alternativo",
                "embed_iframe": "/eventos.html?r=aHR0cHM6Ly9zdHJlYW14OTk2Lm9uZS9nbG9iYWwxLnBocD9jaGFubmVsPXR5Y2ludA=="
              }
            }
          ]
        },
        "country": {
          "data": {
            "id": 3,
            "attributes": {
              "name": "Argentina",
              "createdAt": "2023-11-22T14:52:41.307Z",
              "updatedAt": "2023-11-22T17:59:52.523Z",
              "publishedAt": "2023-11-22T14:54:38.957Z",
              "image": {
                "data": {
                  "id": 29,
                  "attributes": {
                    "name": "argentina.png",
                    "alternativeText": null,
                    "caption": null,
                    "width": 128,
                    "height": 128,
                    "formats": null,
                    "hash": "argentina_2bd748026e",
                    "ext": ".png",
                    "mime": "image/png",
                    "size": 0.92,
                    "url": "/uploads/argentina_2bd748026e.png",
                    "previewUrl": null,
                    "provider": "local",
                    "provider_metadata": null,
                    "createdAt": "2023-11-22T17:59:33.800Z",
                    "updatedAt": "2023-11-22T17:59:33.800Z"
                  }
                }
              }
            }
          }
        }
      }
    },
    {
      "id": 33861,
      "attributes": {
        "diary_hour": "17:30:00",
        "diary_description": "Brasileirão: Vitória vs Vasco da Gama",
        "date_diary": "2026-07-16",
        "deportes": "Futbol",
        "embeds": {
          "data": [
            {
              "id": 263,
              "attributes": {
                "embed_name": "Premiere 2 BR ",
                "idioma": "Portugués",
                "embed_iframe": "/embed/eventos.html?r=aHR0cHM6Ly9sYTE4aGQuc3Uvdml2by9jYW5hbC5waHA/c3RyZWFtPXByZW1pZXJlMg=="
              }
            },
            {
              "id": 28912,
              "attributes": {
                "embed_name": "Fanatiz",
                "idioma": "Español/Alternativo",
                "embed_iframe": "/eventos.html?r=aHR0cHM6Ly9zdHJlYW14OTk2Lm9uZS9nbG9iYWwxLnBocD9jaGFubmVsPWZhbmF0aXoy"
              }
            }
          ]
        },
        "country": {
          "data": {
            "id": 1,
            "attributes": {
              "name": "Brasil",
              "createdAt": "2023-11-22T14:40:01.140Z",
              "updatedAt": "2024-01-07T23:56:59.376Z",
              "publishedAt": "2023-11-22T14:42:50.953Z",
              "image": {
                "data": {
                  "id": 141,
                  "attributes": {
                    "name": "brasil.png",
                    "alternativeText": null,
                    "caption": null,
                    "width": 64,
                    "height": 64,
                    "formats": null,
                    "hash": "brasil_25a533e5f7",
                    "ext": ".png",
                    "mime": "image/png",
                    "size": 0.85,
                    "url": "/uploads/brasil_25a533e5f7.png",
                    "previewUrl": null,
                    "provider": "local",
                    "provider_metadata": null,
                    "createdAt": "2024-01-07T23:56:57.083Z",
                    "updatedAt": "2024-01-07T23:56:57.083Z"
                  }
                }
              }
            }
          }
        }
      }
    },
    {
      "id": 33862,
      "attributes": {
        "diary_hour": "17:30:00",
        "diary_description": "Brasileirão: Botafogo vs Santos",
        "date_diary": "2026-07-16",
        "deportes": "Futbol",
        "embeds": {
          "data": [
            {
              "id": 180,
              "attributes": {
                "embed_name": "Premiere BR ",
                "idioma": "Portugués",
                "embed_iframe": "/embed/eventos.html?r=aHR0cHM6Ly9sYTE4aGQuc3Uvdml2by9jYW5hbC5waHA/c3RyZWFtPXByZW1pZXJlMQ=="
              }
            },
            {
              "id": 15415,
              "attributes": {
                "embed_name": "Fanatiz",
                "idioma": "Español/Alternativo",
                "embed_iframe": "/eventos.html?r=aHR0cHM6Ly9zdHJlYW14OTk2Lm9uZS9nbG9iYWwxLnBocD9jaGFubmVsPWZhbmF0aXoz"
              }
            }
          ]
        },
        "country": {
          "data": {
            "id": 1,
            "attributes": {
              "name": "Brasil",
              "createdAt": "2023-11-22T14:40:01.140Z",
              "updatedAt": "2024-01-07T23:56:59.376Z",
              "publishedAt": "2023-11-22T14:42:50.953Z",
              "image": {
                "data": {
                  "id": 141,
                  "attributes": {
                    "name": "brasil.png",
                    "alternativeText": null,
                    "caption": null,
                    "width": 64,
                    "height": 64,
                    "formats": null,
                    "hash": "brasil_25a533e5f7",
                    "ext": ".png",
                    "mime": "image/png",
                    "size": 0.85,
                    "url": "/uploads/brasil_25a533e5f7.png",
                    "previewUrl": null,
                    "provider": "local",
                    "provider_metadata": null,
                    "createdAt": "2024-01-07T23:56:57.083Z",
                    "updatedAt": "2024-01-07T23:56:57.083Z"
                  }
                }
              }
            }
          }
        }
      }
    },
    {
      "id": 33863,
      "attributes": {
        "diary_hour": "19:45:00",
        "diary_description": "Copa Argentina: Sarmiento vs Boca Juniors",
        "date_diary": "2026-07-16",
        "deportes": "Futbol",
        "embeds": {
          "data": [
            {
              "id": 101,
              "attributes": {
                "embed_name": "TyC Sports",
                "idioma": "español",
                "embed_iframe": "/embed/eventos.html?r=aHR0cHM6Ly9sYTIwaGQuY29tL3Zpdm8vY2FuYWwucGhwP3N0cmVhbT10eWNzcG9ydHM="
              }
            },
            {
              "id": 1211,
              "attributes": {
                "embed_name": "TyC Sports Movil",
                "idioma": null,
                "embed_iframe": "/embed/eventos?r=aHR0cHM6Ly93d3cudGFyamV0YXJvaml0YS54eXovc3czLmh0bWw/Z2V0PWh0dHBzOi8vd3d3LnRhcmpldGFyb2ppdGEueHl6L3JlcHJvL3R5Y3Nwb3J0c2FyZy5odG1s"
              }
            },
            {
              "id": 11337,
              "attributes": {
                "embed_name": "TyC Sports",
                "idioma": "Español/Alternativo",
                "embed_iframe": "/eventos.html?r=aHR0cHM6Ly9zdHJlYW10cC5zYnMvZ2xvYmFsMS5waHA/c3RyZWFtPXR5Y3Nwb3J0cw=="
              }
            },
            {
              "id": 29621,
              "attributes": {
                "embed_name": "Fanatiz",
                "idioma": "Español/Alternativo",
                "embed_iframe": "/eventos.html?r=aHR0cHM6Ly9zdHJlYW14OTk2Lm9uZS9nbG9iYWwxLnBocD9jaGFubmVsPWZhbmF0aXo0"
              }
            },
            {
              "id": 12912,
              "attributes": {
                "embed_name": "TyC Sports OP2",
                "idioma": "Español/Alternativo",
                "embed_iframe": "/eventos.html?r=aHR0cHM6Ly9zdHJlYW14OTk2Lm9uZS9nbG9iYWwxLnBocD9jaGFubmVsPXR5Yw=="
              }
            },
            {
              "id": 22329,
              "attributes": {
                "embed_name": "TyC Sports Internacional",
                "idioma": "Español/Alternativo",
                "embed_iframe": "/eventos.html?r=aHR0cHM6Ly9zdHJlYW14OTk2Lm9uZS9nbG9iYWwxLnBocD9jaGFubmVsPXR5Y2ludA=="
              }
            }
          ]
        },
        "country": {
          "data": {
            "id": 3,
            "attributes": {
              "name": "Argentina",
              "createdAt": "2023-11-22T14:52:41.307Z",
              "updatedAt": "2023-11-22T17:59:52.523Z",
              "publishedAt": "2023-11-22T14:54:38.957Z",
              "image": {
                "data": {
                  "id": 29,
                  "attributes": {
                    "name": "argentina.png",
                    "alternativeText": null,
                    "caption": null,
                    "width": 128,
                    "height": 128,
                    "formats": null,
                    "hash": "argentina_2bd748026e",
                    "ext": ".png",
                    "mime": "image/png",
                    "size": 0.92,
                    "url": "/uploads/argentina_2bd748026e.png",
                    "previewUrl": null,
                    "provider": "local",
                    "provider_metadata": null,
                    "createdAt": "2023-11-22T17:59:33.800Z",
                    "updatedAt": "2023-11-22T17:59:33.800Z"
                  }
                }
              }
            }
          }
        }
      }
    },
    {
      "id": 33864,
      "attributes": {
        "diary_hour": "20:00:00",
        "diary_description": "Liga MX: Necaxa vs Atlante",
        "date_diary": "2026-07-16",
        "deportes": "Futbol",
        "embeds": {
          "data": [
            {
              "id": 774,
              "attributes": {
                "embed_name": "FOX Deportes",
                "idioma": "Español",
                "embed_iframe": "/embed/eventos.html?r=aHR0cHM6Ly9sYTE4aGQuc3Uvdml2by9jYW5hbC5waHA/c3RyZWFtPWZveGRlcG9ydGVz"
              }
            },
            {
              "id": 15516,
              "attributes": {
                "embed_name": "Fox Deportes",
                "idioma": "Español/Alternativo",
                "embed_iframe": "/eventos.html?r=aHR0cHM6Ly9zdHJlYW10cC5zYnMvZ2xvYmFsMS5waHA/c3RyZWFtPWZveF9kZXBvcnRlc191c2E="
              }
            },
            {
              "id": 18036,
              "attributes": {
                "embed_name": "Fox ONE",
                "idioma": "Español/Alternativo",
                "embed_iframe": "/eventos.html?r=aHR0cHM6Ly9zdHJlYW10cC5zYnMvZ2xvYmFsMS5waHA/c3RyZWFtPWZveG9uZQ=="
              }
            },
            {
              "id": 12835,
              "attributes": {
                "embed_name": "Fox ONE OP2",
                "idioma": "Español/Alternativo",
                "embed_iframe": "/eventos.html?r=aHR0cHM6Ly9zdHJlYW14OTk2Lm9uZS9nbG9iYWwxLnBocD9jaGFubmVsPWZveG9uZTE="
              }
            },
            {
              "id": 24428,
              "attributes": {
                "embed_name": "Fox Deportes OP2",
                "idioma": "Español/Alternativo",
                "embed_iframe": "/eventos.html?r=aHR0cHM6Ly9zdHJlYW14OTk2Lm9uZS9nbG9iYWwxLnBocD9jaGFubmVsPWZveGRlcG9ydGVz"
              }
            }
          ]
        },
        "country": {
          "data": {
            "id": 5,
            "attributes": {
              "name": "México",
              "createdAt": "2023-11-22T15:15:54.001Z",
              "updatedAt": "2024-01-07T23:56:44.462Z",
              "publishedAt": "2023-11-22T15:16:00.799Z",
              "image": {
                "data": {
                  "id": 140,
                  "attributes": {
                    "name": "bandera.png",
                    "alternativeText": null,
                    "caption": null,
                    "width": 64,
                    "height": 64,
                    "formats": null,
                    "hash": "bandera_fbc29cb609",
                    "ext": ".png",
                    "mime": "image/png",
                    "size": 1.04,
                    "url": "/uploads/bandera_fbc29cb609.png",
                    "previewUrl": null,
                    "provider": "local",
                    "provider_metadata": null,
                    "createdAt": "2024-01-07T23:56:40.086Z",
                    "updatedAt": "2024-01-07T23:56:40.086Z"
                  }
                }
              }
            }
          }
        }
      }
    },
    {
      "id": 33865,
      "attributes": {
        "diary_hour": "22:00:00",
        "diary_description": " Liga MX: Tijuana vs Tigres UANL",
        "date_diary": "2026-07-16",
        "deportes": "Futbol",
        "embeds": {
          "data": [
            {
              "id": 206,
              "attributes": {
                "embed_name": "TUDN USA",
                "idioma": "Español",
                "embed_iframe": "/embed/eventos.html?r=aHR0cHM6Ly9sYTE4aGQuc3Uvdml2by9jYW5hbC5waHA/c3RyZWFtPXR1ZG4="
              }
            },
            {
              "id": 1202,
              "attributes": {
                "embed_name": "TUDN USA Movil",
                "idioma": null,
                "embed_iframe": "/embed/eventos?r=aHR0cHM6Ly9yb2phZGlyZWN0YXR2ZS5jb20vc3czLmh0bWw/Z2V0PWh0dHBzOi8vcm9qYWRpcmVjdGF0dmUuY29tL3JlcHJvL3R1ZG51c2F0di5odG1s"
              }
            },
            {
              "id": 10691,
              "attributes": {
                "embed_name": "TUDN US",
                "idioma": "Español/Alternativo",
                "embed_iframe": "/eventos.html?r=aHR0cHM6Ly9zdHJlYW10cC5zYnMvZ2xvYmFsMS5waHA/c3RyZWFtPXR1ZG5fdXNh"
              }
            },
            {
              "id": 23910,
              "attributes": {
                "embed_name": "Fox ONE",
                "idioma": "Español/Alternativo",
                "embed_iframe": "/eventos.html?r=aHR0cHM6Ly9zdHJlYW10cC5zYnMvZ2xvYmFsMS5waHA/c3RyZWFtPWZveG9uZQ=="
              }
            },
            {
              "id": 28360,
              "attributes": {
                "embed_name": "Fox ONE OP2",
                "idioma": "Español/Alternativo",
                "embed_iframe": "/eventos.html?r=aHR0cHM6Ly9zdHJlYW14OTk2Lm9uZS9nbG9iYWwxLnBocD9jaGFubmVsPWZveG9uZTI="
              }
            },
            {
              "id": 24547,
              "attributes": {
                "embed_name": "TUDN US OP2",
                "idioma": "Español/Alternativo",
                "embed_iframe": "/eventos.html?r=aHR0cHM6Ly9zdHJlYW14OTk2Lm9uZS9nbG9iYWwxLnBocD9jaGFubmVsPXR1ZG51cw=="
              }
            }
          ]
        },
        "country": {
          "data": {
            "id": 5,
            "attributes": {
              "name": "México",
              "createdAt": "2023-11-22T15:15:54.001Z",
              "updatedAt": "2024-01-07T23:56:44.462Z",
              "publishedAt": "2023-11-22T15:16:00.799Z",
              "image": {
                "data": {
                  "id": 140,
                  "attributes": {
                    "name": "bandera.png",
                    "alternativeText": null,
                    "caption": null,
                    "width": 64,
                    "height": 64,
                    "formats": null,
                    "hash": "bandera_fbc29cb609",
                    "ext": ".png",
                    "mime": "image/png",
                    "size": 1.04,
                    "url": "/uploads/bandera_fbc29cb609.png",
                    "previewUrl": null,
                    "provider": "local",
                    "provider_metadata": null,
                    "createdAt": "2024-01-07T23:56:40.086Z",
                    "updatedAt": "2024-01-07T23:56:40.086Z"
                  }
                }
              }
            }
          }
        }
      }
    }
  ]
}